ripple_detection/__init__.py
ripple_detection/_version.py
ripple_detection/core.py
ripple_detection/detectors.py
ripple_detection/simulate.py
ripple_detection/ripplefilter.mat
ripple_detection-1.7.0.dist-info/METADATA
ripple_detection-1.7.0.dist-info/WHEEL
ripple_detection-1.7.0.dist-info/licenses/LICENSE
ripple_detection-1.7.0.dist-info/RECORD
