Metadata-Version: 2.4
Name: ripple_detection
Version: 1.7.0
Summary: Tools for finding sharp-wave ripple events (150-250 Hz) from local field potentials.
Project-URL: Homepage, https://github.com/Eden-Kramer-Lab/ripple_detection
Project-URL: Repository, https://github.com/Eden-Kramer-Lab/ripple_detection
Project-URL: Issues, https://github.com/Eden-Kramer-Lab/ripple_detection/issues
Author-email: Eric Denovellis <edeno@bu.edu>
License: MIT License
License-File: LICENSE
Keywords: LFP,hippocampus,neuroscience,ripple,sharp-wave
Classifier: Development Status :: 5 - Production/Stable
Classifier: Intended Audience :: Science/Research
Classifier: License :: OSI Approved :: MIT License
Classifier: Operating System :: OS Independent
Classifier: Programming Language :: Python :: 3
Classifier: Programming Language :: Python :: 3.10
Classifier: Programming Language :: Python :: 3.11
Classifier: Programming Language :: Python :: 3.12
Classifier: Programming Language :: Python :: 3.13
Classifier: Topic :: Scientific/Engineering
Requires-Python: >=3.10
Requires-Dist: numpy>=1.24
Requires-Dist: pandas>=2.0
Requires-Dist: scipy>=1.10
Provides-Extra: dev
Requires-Dist: black[jupyter]>=23.0.0; extra == 'dev'
Requires-Dist: flake8>=6.0.0; extra == 'dev'
Requires-Dist: hypothesis>=6.0.0; extra == 'dev'
Requires-Dist: mypy>=1.8.0; extra == 'dev'
Requires-Dist: pytest-cov>=4.0.0; extra == 'dev'
Requires-Dist: pytest-snapshot>=0.9.0; extra == 'dev'
Requires-Dist: pytest>=7.0.0; extra == 'dev'
Requires-Dist: ruff>=0.3.0; extra == 'dev'
Provides-Extra: examples
Requires-Dist: jupyter>=1.0.0; extra == 'examples'
Requires-Dist: jupyterlab>=3.0.0; extra == 'examples'
Requires-Dist: matplotlib>=3.5.0; extra == 'examples'
